setup.py
gdapi/__init__.py
gdapi/apirequest.py
gdapi/errors.py
gdapi/gdapi.py
gdapi/utils.py
gdapi.egg-info/PKG-INFO
gdapi.egg-info/SOURCES.txt
gdapi.egg-info/dependency_links.txt
gdapi.egg-info/requires.txt
gdapi.egg-info/top_level.txt
script/download_to_somewhere.py
script/upload_to_root.py