Metadata-Version: 1.1
Name: gdapi
Version: 0.2.2
Summary: Google Drive API Wrapper
Home-page: https://github.com/clsung/gdapi
Author: Cheng-Lung Sung
Author-email: clsung@gmail.com
License: UNKNOWN
Download-URL: http://pypi.python.org/pypi/gdapi
Platform: UNKNOWN
